axon/__init__.py
axon/_ops.py
axon/_random.py
axon/_utils.py
axon/base.py
axon/dtypes/convert.py
axon/dtypes/dtypes.py
axon/helpers/functional.py
axon/helpers/ops.py
axon/helpers/shapes.py
axon/helpers/utils.py
axon/micro/__init__.py
axon/micro/_cbase.py
axon/micro/base.py
axon/micro/libscalar.so
axon/micro/nn.py
axon_pypi-1.0.3.dist-info/LICENSE
axon_pypi-1.0.3.dist-info/METADATA
axon_pypi-1.0.3.dist-info/WHEEL
axon_pypi-1.0.3.dist-info/entry_points.txt
axon_pypi-1.0.3.dist-info/top_level.txt
axon_pypi-1.0.3.dist-info/RECORD
