Metadata-Version: 2.1
Name: axon-pypi
Version: 1.0.3
Summary: Multi-dimensional array creation & manipulation library like numpy written from scratch in Python along with a scalar level autograd engine written in C/C++ with Python wrapper
Author: shivendra
Author-email: shivendra <shivharsh44@gmail.com>
License: MIT
Classifier: Development Status :: 5 - Production/Stable
Classifier: Intended Audience :: Developers
Classifier: Programming Language :: C
Classifier: Programming Language :: C++
Classifier: Programming Language :: Python
Classifier: Programming Language :: Python :: 3.8
Classifier: Programming Language :: Python :: 3.9
Classifier: Programming Language :: Python :: 3.10
Classifier: Programming Language :: Python :: 3.11
Classifier: Operating System :: OS Independent
Classifier: License :: OSI Approved :: MIT License
License-File: LICENSE
